{
    "run_id": 1744062859000,
    "start_time": "2025-04-07T21:54:19+00:00",
    "weather": {
        "temperature_c": 17.7,
        "condition": "局部多云 ⛅️",
        "wind_speed_kmh": 3.6
    },
    "route": {
        "encoded_polyline": "y`zkCwqjrT@@@?B@B@B@B@B@BBB@BBBBB@BBB@D@B@B@B@BBB@B@B@BBB?B@D@B?D@B?D?D?DAB?D?B?B@B@@@BB?@@B@B@B?B@B?B?@?B?@A@ABA@A@A@A@C?A?C?A?CAC?C?A?C?C?A?C?C@C?CAA?C?CAC?C?C?CAC?C?C?A?CACACCACCGCGCECGCECCCCECACCACACAAAC?CCAACACACAAACACCCACACACACAAACACACACACCCCCCACAEAEAECEAECECCACCECCCCCACCCCACCEACCEAEACCEACCEACCCCCCACCCCCACCAACACCCACACAC?CACAE@C?C?E@C@C@CBCBCBCBCDCBABCBCDABC@CBCBCBCBCBC@C@C@C@C@C@A@C@CBA@CBABCBCBABCBABC@ABCBCBA@CBA@CBABCBABC@ABCBC@ABCBC@CBCBA@CBC@CBC@ABC@C@CBC@C@C@C@C@C@C?C@A@C@C@C@C@C@A@C@CBC@CBC@ABC@CBC@CBC@CBC@ABC@CBC@ABC@ABCB?DABABABABABABA@ABAB?BABA@A?C@A@A?C?A?A@C?C@C@C@C?C@C@C@C@CBA@C@CBCBC@ABCBC@CBCBC@ABC@CBC@CBABC@CBCBA@CBC@CBA@C@CBA@CBC@ABCBABABCDABABABABCBABC@ABCBC@CBABC@CBC@E@E@E@E@E@CBC@CBC@CBA@C@C@C@CBA@C@CBC@ABC@CBABABCDABCBABCDCBCBCBCBCBC@CBCBA@CBCBCBC@CBCBC@CBCBCBC@C@CBA@CDABADADCBCBCDCBCBCBCBCBC@CBCBA@CDABADAD?DADADADCDCBC@CBE?C?E?C?E?C?C@C@CBCBABCBCBABCBCBC@CBCBC@CBC@C@CBC@CBCBCBCBCBCBCBC@CBABC@CBC@C@C@C@C@C?A@C@C@C@E?C@C@E@C@EBC@E@E@CBE@C@C@E@C@C@C@E@C@CBC@C@C@C@C@CBE@C@CBC@C@E@CBC@CBE@CBC@C@CBC@C@EBC@CBC@C@CBC@CBC@ABC@C@CBC@EBC@C@CBC@CBC@C@CBC@E@CBC@E@CBC@E@C@C@C@E@CBC@EDCBEBEBE@C@EBC@E@C@C@C@C@C@C@C@CBE@C@EBE@C@E@C@C@E@CBC@E@CBC@CBC@CBCBC@CBABABCBABABADABCBABCBCBCBCBCBC@CBABC@CBC@C@E?C@E?E@C@E@C@CBC@EBCBCBCBC@EBCBCBCBCBCBCBCBCBCBE@CBEBC@E@EBC@C@CBCBC@CBEBC@E@C@E@E@C@E@E@E@C@C@C@A@CBA@C@A@C@A@C?C@C@C?C@C@C?C@C@E?C@C@A@C@C@CBC@A@C@C?C@C@C@CBC@C@E@C@C@C?C@A@CBC@C@C@C@C@ABC@C@C@C?C@C@C@E@EBC@C@CBC@C@C@E@C@E?E@C@E?C@CBABC@ADCBABABABCBC@E@CBC@CBC@?DAB?B?B?D?B?D?B?D?B?D@B?B?D?B?B?D?B?D@B?D?B?D?B?DAD?B?D?B?D?B?B?D?B@D?B@B?D@B@B?B@B@B?B@D?B@B@B@B?B@D?B?B@D?B?D?B?D@B?D?D@B?D?D?D?BAD?D?B?D?D?B@D?B@D@B@B@D@B@B?D@B@D?B?D@B?D@B?D@B@D?B@D?B@D?D@B@D?B?D?BAD@B?D?B@D?B@D@B@D?B@D?B@B@D@B?D@B@D@B@D@D@B?D@D@B@D@D@B@D@BBB@@@B@@@@@@@B@@@B@@?B@B@B@BBB@D@BBDBB@DBD@BBDBD@DBB@D@B@B@D?BBB@DBBD@BBDBD@BBBBBBBB@B@BBB@B@BBB@DBB@B@BB@@B@B@B@B@B@B?B@B@B@B@B@B@B@B@B@D@B@D@B@B@B@BBB@B@DBB?D?BADABCBCBC@CBC?A@C?ADABADAFAD?F@D?D@D@DBD@D@D@B@D@D?D@B@D@D?B@D@B?B@B@D@B@B@D@B?D@B@D@D?D@D@D@D@B@DBD@B@DBDBD@DBBBD@BBD@DBBBD@DBD@D?D@BADABABCBABCBC@CBC@EBCBCBC@CBABABAB?B@B?B@D?B@B@D?B?B@B?B@D?B@D@B@B@D@B@B@BBD@BBB@BBD@BBB@D@B?D@D@B?D@B@D@D@B@D@B@D@DBB@B@DBB@D@B@B@BBD@B@B@B?D@B@B@B@DBB@D@B?B@B@B@B@B@BB?@@B?@ABABAB?BAB@B?@BB@@B@D?B@DAB?DA@CBC@EBC@E@E@CBE@EBC@EBCBE@CBCBE@CBCBCBCBC@CBABCBAB?B?B?B@D@B@B@B@DBB@BBB@D@BBB@B@DBB@B@B@D?B?BCBA@C@CBC?C@ABC@A@AB?B?B@D@D@D@D@D@D?D@D@D@D?D@D@D?D@D@D?B@D@D?D@D@B@D?D@D@D@D?D@D?D@D?B@D?D@B@D@B@D@B@B@D@B@B@B@D@B@D?B@D@B?D@B@D@B?D@B@D@B?B@D@B@D@B@DBD@B@DBB@D@BBB@DBB@B@D@D@B@D@D@D@D?D@D@D@D@DBD@D@B@D@D@D@D@D@B@D@B@D@B@D@B@DBB@D@B@D@B@B@D?B?D@D?D?B@D@D?B@D@D?B@D@D@D@B?D@B@D?B@D@B@D@B@D@D@D@D@D?D@D?D@D@B?F@D@B?D@D@D?D@D@D@B?D@D@D@B?D@D@B?D@B@D?B@D?D?B@D?D@B?D@B@DBD@B@D@D@D@D?D@B@D?D@D?D?D@D?D@D?B@D@D?D@B?D@D@B?D@B@D?D@B@D?B@D?B@D?D?D?B?D?D?D@D?B?D@D?B@D?B@B@B?D@B?B@D?B@D?D?D?B?D?D?B?D?BAD?DABAD?BABADAB?BABAB?BAB?BABABABCBC@CBC@EBC@E?C@E@C@C@E@C@C@E@C@C@E@C@E?C@C@C@E@C@C@E@C@E@C@E@C@E@C@E@C@E@C@C@CBCBABABAB?D?B?D?DAD?BADADA@CBCBC@E?C@E?C@E?E?C@E@C?E@C@E?C@E@C@C@E?C@E@C@E@C@E@C@E?C@E@C@E@C@C?E@C@E@C?C@E@C@C?E@C@E?C@E?C@C?E@C@C?E@C@E?C@E@C?C@E?C@C@C?E@C?C@E@C?E@C?C@E?C@E?C@C@C?E@C?C@C?E@C?C@E?C@C?E@C?C@E?C@E?C@E?C@E?C@C?E@C?E@C?C@E?C@C?E@C?C@C?E@C?C@C@E?C@C?E@C?E?C?E?C?E?E?C?E?C?CACACCCCACCCCCACCAC?CAE?C?C?E?CAC?C?E@C?E@C?C@E@C?E@C?E?C?E?C?C?CAE?CAC?EACAC?EACAC?CACAEACACAEACAEACAEACACAEACACACACACACCCAEACACACACAE?CAC?EACAE?CAE?C?EAC?CAE?C?EAC?E?C?C?E?C?C@E?C?C@E?C?E@C?E?C@C?E@C?C@E@C?E@C?C@E?C@C?E@C?E?C@E?E@C?E@C@E?C@E@E?C@E@C?C@E?C@E@C?E@C?C@E@C?E@C@C@E@C@C@C@E@C@C@CBC@C@CBCBC@CBABCBCBABCBABABABAB?D?B?D?B?DAB?D?DABADADABCDADCBCDABADCBABCDABCBCBA@CBCBC@CBA@CBC@CBE@C@C@C@C@E@C@C@C@E@C@C@C@ABA@@D?B?D@D@B?D?D?BCBA@E@C@C@E?E@C@E?C@E@C?E@C?C@E@C?E@C?C@E?C@C@C?E@C@C@C?E@C@C@C@E?C@E@C?C@E@C?E@C@C@E@C?E@C@E@E@C?E@C@E@C@E@C?C@E@C@E?C@E@C@C@E?C@C@E@C?C@E@C@C@E?C@E@C@E?C@C@E@C?E@C@E@C@E?C@E@C?E@C@E@C@E?C@E@C?C@E@C?E@C@E?C@C@E@C?E@C?E@C@E@C?E@C@E@C?E@C@E@C@E@C@E@C@E@C@E@C@E?C@E@C@E@C?E@C@C?C@E@C?C@E@C?E@C@E@C?C@E@C@C@E?C@C@E@C@C?E@C@C@E?C@C@E@C?C@E@C?C@E@C@C@E?C@E@C@E?C@E?C@E?C@E?C?E?C?C?C?C?C@E?C?C?C@C?C?E?C@C?C?E@C?C@C@C@C@C@C@C@C@C@C@C@A@C@C@C@C@C@C@C@E@C@C@CBE@C@C@CBC@C@CBC@C@EBC@C@CBC@CBC@C@CBC@C@CBC@CBC@C@CBC@EBC@CBC@EBC@CBC@E@CBC@CBE@CBC@E@CBC@C@E@CBC@E@C@E@CBC@E@C@CBC@EBCBC@CBCBC@CBCBC@CBCBC@CBABADABADABCBADCBABABCD?B?B?B?DABABCBA@EBC@C@EBC@E@CBC@C@E@CBC@E@CBC@C@E@CBC@C@CBE@C@CBC@C@EBC@C@CBC@C@CBCBC@CBC@CBA@CBC@CBC@C@C@C@E@C?C?E@C?C@C@E@C@CBC@C@C@CBC@CBC@E@CBC@CBC@CBC@C@CBC@C@CBE@CBC@C@EBC@CBE@C@CBC@E@C@CBC@C@CBE@C@CBC@EBC@CBC@E@CBC@EBCBA@ADABAD?B?D?D?DADABABCBABE@CBCBC@EBC@CBC@CBC@EBCBCBC@CBC@CBCBC@CBA@CBC@CBCBC@CBC@ABCBCBC@CBCBCBC@ABCBCBCBABC@CBCBCBCBC@CBCBCBCBCBCBC@CBCBCBCBABCBC@CBCBC@CBABCBC@CBABCBCBA@CBCBCBABC@CBABCBC@CBC@CBC@E@C@E@C@C@E?C@E@C?E?C?E?CAE?CACAACCAACCEAACCC?CAC?C@E?C?EAC?ECCACECCCCACCECCAEACCEACAECCACCEACCCAECCAEACAECCAEACCCACAECCACACAEACAE?EACAEAEAEACAEAEAEACAEACCEAEACAEACCEACAEACCEACAEACAEACCEACAEACACCEACAEACACCEACAEACACCEACAEACAEACCCAEACAEACAE?CAEACAEACAEACAEACAEACAEACAEAECCAEACAEACAEACAEACAEACACAEACAEACAEAEACAEACAEACAEACACAEACACAEACAEACACAEAC?EACAEACACAE?CAEACAEACAEACAE?CAEACAE?EACAECCAEACAEACCEACAEACCEACAEACAEACCEACAEACAEACAECCAEAEACCEACAEACAECCAEACAEACACAEAC?EAEAC?EACAEACACAEACACACACAA?CAAAEAG?E?I?I?I@K?I@KAI?KCEEGGKIKIIGGEEGECECCCEACCEAEACAEAEACAECEACAEAECCAEAEACAEAEACAECCAEAEACAEACAEACAEACAEACAEAEACAEACAEACAEACAEACAEACAE?ECCAEACAEAC?EACAEAEACCEAEACAEAC?EAEACAEACAEAE?CAEACAEACAECCAEACACAEACAEACAEACAEAC?EACAEACCEAEAC?EACAEACAEACAE?CAEACACAE?CACAC?CACAE?CAEACAEAEAEACAEAEACAEAEACAEAEACAEACAEAC?EACAEAEACAEACAEAEACAEAEAE?CAEAEACAEACAEACAEACACAEAC?EACAEACACCEACACAEACAEACCEACACAEACAEACAEACAEAC?EAEACAEAEACAEAEAEACCEAEACAECCAEAEACAEACAEACAEACAEACAEAEACAEACAEAEACAEAEACAEAC?EACAEAC?EAC?CAE?CACAEACAEAEAEACAECEACAEACAECEACAEAEACAECEACAEACAEAECCAEACAEAEACAEACAEAEACAECCAEAEACCEAEAEACAECEACAEACAECCAEACAEACAEACAEACAEACAEAEACCEACAECEACCEACCEACAECCAEACAEAEACAEACAEACAEACAECCAEACAEAEACCEACAEACAECCAEACAEACAEACAEACAEACAEACAEACAEACACAEACAEACACAEACAC?EACACAEACACAEACACAEACACAEACAC?EACAEACAEACAEACAEACCCAEACAEACCEACAEACAEACACAEACCEACAEACAEACAECCAEACAEACACACAEAC?CAEACAEACCEACAECCAEACCCAEACAEACAEACCEAEACAEAEACCEACCEACAECCAEACAEACACAEACAEAEACAEAEAECCAEAEACAEAEACAECEACAEAECCAECEACAEACCEAEACACCEACAEACCCAEACCEACAECCAEAECCAEAECCAEACAECEACAEACAEACAEAE?CAECEACAEACACACACACAEACACAC?EACACACACACACAEAEACAEAEAEACAEAEAEACAEAEACCEACCEACCEACAEACAEACAEAC?CAEACAC?EACAEACCEACAEACACAEACAEACCEACAEACAEACACAEACAECCAEACAEACAEACAECCAEACCEAECCAEACCEACAEACAEAEACAEAEACAEACAEAC?CCEACAEACAEACAEAECCAEACAEACAEAC?A?C?A?A@A?C?AAC?CEECEEECGEICGCGAGAGAEAEAEACAEACACAE?CAEAEACCE?EACAEAEAC?EAEAE?CAEAEAEAC?EAEAEACAEAEAE?EAEAC?EAEAE?EAE?CAE?EAE?E?C?EAE?C?EAEAE?CAE?EAE?E?CAE?E?EACAE?EAE?EAC?E?EAE?E?CAE?E?E?EAE?C?EAE?E?C?EAC?E?E?C?EAC?E?C?E?CAE?C?E?EAC?E?CAE?EAC?E?EAC?EAE?E?CAE?E?E?C?E?E?C?E?EAC?E?E?EAC?EAE?EAE?C?E?E?E?C?E?E?E?CAE?E?E?C?E?E?E?E?CAE?E?C?EAE?C?E?E?E?C?E?E?EAE?C?E?E?E?C?E?E?E?E?C?E?E?E?E?E?E?E@C?E?E?E?E@C?E?E?C@E?E?E?E@C?E?C?E?E?C?E?E?C@E?E?E?E?C?E?E?E?E?C?E?E?E@C?C?E@C?E@C?C?E?E@C?E?E?E?E?E?E?E?E?E?E@E?E?E@C?E?E@E?E?E@E?C?E@E?E@E?E@E?E@C?E?E@E?E@E@E?E@C?E@E?C@E?E@E?C?E@E?E@E?E@C?E@E?E@E?E@C?E@E?E@C?E@E@C?E@E?C@E@E?C@E?E@C?E@C?E@E?C@E?E@C?E@E@C?E@C?E@E@C?E@C@E?C@E@E?C@E@C?E@C@E?E@C@E?E@C@E@C?C@E@C@E@C@E@C@E?C@E@C@E?C@E?E@C@E?E@C@E@E@C?E@C@E@E@C@E?C@E@C@E@C@C@E@C@E@C@E@C@E@C?E@E@C@E@C@E?C@E@C@E@C?E@C@E@E@C?E@C@E@E@C@E@C@E@C@E@E@CBE@C@C@EBC@EBC@CBE@CBC@C@EBC@CBC@E@C@E?C@E?E?E@E?E@C@E@E@CBC@E@CBC@E@C@CBE@E@E@E@E@E@E?E@E@EBE@C@E@E@E@C@E@E@C@E@C@EBC@E@C@E@E@C@E@C@C@EBC@C@E@C@E@C@E@C?E@E@C@E@C@E@C@E@E@C@E@EBC@E@E@C@E@E@C@EBC@E@C@E@E@C@EBC@C@E@C@EBC@E@C@C@E@E@C?E@E@E@E@C@E@E@E@C@E@C@E@C@C@E@C@C@C@E@C@C@C@E@CBC@E@C@E@E?E@C@E@E@E@E@C@E@C@E@C@C@E@C?C@E@C@E@CBE@C@E@CBE@C@E@CBE@C@E?C@E@C?C@E@C?C@E@C@E@C@E@CBE@C@E@EBC@E@E@E@CBE@C@C@E@C@E@E@C@E@E@E@C@E@E@E@C?EBE@C@E@C@E@C@E@C@C@E@C@E@C?E@C@E@C?E@C@E@C@C@E@C@C@C@E@C@C@E@C@E@C@C@E@C@C@E@C@CBE@C@CBE@C@CBE@C@E@C@E@CBC@E@C@EBC@E@C@EBC@E@C@EBE@C@E@C@EBC@E@CBE@E@CBE@E@C@EBC@E@E@C@EBC@E@C@CBC@E@C@CBC@C@C@C@A@A@?@?B?@@B@@@B?B?BA@ABABABAB?D?B?D@D@BBD@D@B@D?D@B@D@B?D@B@D@B?D@B@D@B@B?D@B@B?D@B@B@B?B@B?B?B@B?@?B?@AB?B?B@B?D@B@D@B@D@D@D@D@D@D@D@D@D@B@D@B@D@B@D@B@D@B@B@B@D?B@B@D@B@B@B@B@B@D@B@B@B@D?D@D@B?D@B@D@B@B@B@DBB@B@B@D@B@D?B@D@B@B@B@D@B?B@B@BBB@B@B@BBB@BBB@DBBB@BBB@D@B@B@B@B@@BB@@B@B@B@D@B@DBD@BBDBB@BBD@BBB@B?D@B@D@B?D@DAD?D?FADAD?FAD?D?B?D@B?BBB@BBBBB@D@B@D@B@D@B@D@D?B@D@B@B@B@D@BB@@BBB?@@B?BAB?DABAD?B?D?D?B@B?D@B@B@D@B@D@B?D@D@D?B@D@D?B@D@B@D@B?D@B@B@D@B@B@D@B@B@DBB@B@D@B@D@D@B?D@D@B@D@B@D?B@D@B?B@D@B@B@D@B@B@B@B@BBB@B@D@B@D?D?B?D@D?B@D@B?B@B@D@B@B@B@D@B@D@B@B@D@B@D@B@D@B@B@DBB@D@B@B@B?D@B@B@D@B?BBBBB@BBB@BBB?B@D@B@D@D@BBD@B@D@B?D@D@B@D?B@D@B?D@D@B?D@D?D@D?D@B?D?D?B@D?D@B?D?D@B?D@B?B@D?B@B@B@D@B@B@D?B@B?D@B@B?D@B@D?D@B?D?B@D?D@B?D@B?D@D?B@D?B@D?B@B@D?B?D?B@B?B@B@B@@BBB@B@B@D@B?D@B@D@B?B@B?B@BAB?B?B?B@B?BBB@@B@B@DBB@B@D@B@B@D@B@DBB@D?B@D?DABADABADCBABABCBABABCBC@ABCBABCBCBA@ADABCBABABABABABADABABADABAD?B?DAB?BAD?BAD?BAD?BAB?D?B?D?B?B?D@B?B?D?B?B?D?B?B?D?B?D?B?D?B?D?B?B?D?B@B?D?B?B?DAB?B?B?DAB?B?DAD?B?D?D?D?D?B?D?DAB?D?B?D?B?D@B?B?D?B?D?D?BAD?D?B?D?D?B?DAB?D?B?DAB?D?BAD?B?DAB?DABAD?BAD?BAB?BAB?BABABADABADABADAD?BADABABCDABABABCBABAD?BABABABADABAB?DABADABADABAB?DAB?BADABADABABADABABABABABA@ABABABABABAD?B?D?B@D?B@D@BBD@BBBB@DBB@DBB@D@D@B@B@B@B@B?B@D@B@B@D@B@B@@@B@B@BBB@@D@B@DAB?D?DADAB?DADABCBABABABAB?BAD?BAD?BAD?BADABABABABABCBABABAB?@ABAB?@ABA@ABA@AB?@ABABABABABABABABABA@ABAB?@AB?BAB?BAD?BADADABADABCBABCBADABABADABAD?DABAD?DABABAD?BABABABADABAB?BAB?BA@?BABCBCDCDCBEDCDCDCDCFADCDADABADADCDABADABADADABABCBADCBABCDABCBADCBADCBADCBADCBABADCDABCDADCBADCBADCBADABADCD?DAB?D?DAD?BAD?DADADABADCDABADCDABADADADADADADABADADABADABADABAD?BAB?BA@A@ABA@ABABADABADCBABCDCBADABADABADABAD?BADABAB?BABABABABA@?BABAB?BAB?BABABADABABCDCBABCBCBCBABCBABAB?@AB?BA@?BABABABAB?BAD?B?D?D?D?D@D?D?F?D?D?D?D?B?D?D?B?D?B?D?BAD?BADAB?DAB?D?DAB?D?DAD?BAD?BAB?D?B?D?B?D?D?FAD?D?FAD?DAF?DABADAD?BAB@D?D@B@DBB@BBBB@B@D@B@D@B@B@D@B@B@DBB@D@B@B@DBD@B@D@B@DBD@B@D@D@D@D@D@D@D?D@B@D@B@D@B@BBD@B@D@B@B?D@B@D@BBD?B@B@D@B?D?D@D?D?D?D@D?D@B@D@D@B@D?D@D@D?D?F@D?D@D?D@D@D@D?D@B@D@B@DBB@B@BBD@B@D@B@D@D@D@DBD@BBD@D@D@D@D?D?F@D?F@D?F@D?D@D?FBD@DBD@D@F@D@D@D@F@D@D@D@D@B@D@D@DBB?D@B@D@D?B@D@D?D@D@B?D@D@D@B?D@D@D?B@D?D@D?B@D?B@D?B@D@B@DBB?F@D?H?F?D?F?D?D@D?D@B?D@B?D@D@B?D@B?D@B?D@D?D@B@D?B@B@D@B@B@BBB@B@B@B@D@B@BBD@B@D@B@B@B@D@BBB@D@BBB@DBB@BBB@BB@B@B@B?D?B?B?DAB?BAD?BAD?BABADABABABAB?BABABABABABAD?DABAD?DAD?DABAB?DCBADABCBADCBADCBCBCDABCBCDABCBADABCBADABADABABADABABADADCBABADA@ABABABABABADCBADABAD?B?B?D?D@B?D@D?D?D?FAD?DAD?BADABABCDABABCDABABABADABABCBADABADADADAD?D?B?D@D?B?D?B@D?BAB?D?B?DAB?DAB?DABADADABAD?D?D?D?D@B?D@D@D?D@D?D@BAB?BA@CBCBCBABCDAB?DADABADADAB?DADADABADADADABAD?D?D?D@B?D@B?D?B?D?B?B?DABAB?DAB?BAB?B?B?B?D?B?B?BAB?DABAB?BCBABCBA@E@C@E?E@E?E@C@CBC@ABAB?BABABA@C@C?E?E?G?E@E@C?EBA@CBA@A@C@C?A@C@C@AB?@AB@B@@@BBB@BBB@BBDBB@DBBBDBBBBBB@DBB@BBB@B@DBB@BBB@BBB@D@B@BBB@BB@B@D?D?D?D?D?D@D?D@B@D@DBDBBBDBBDDBBDBDBD@B@D@D?D?D?D?BAD@D?B?D?D@D?B?D@D?B?D?D?B?D?D?D?D@D?B@D@BBBD@B@D@D?D?D?F?D?D?D?D@B@D@D@D@D?B@D@B@D?B?D@D?D?DAD?D?D?B?DAD?D?B?D?DAB?D?D?B?D?B?D?D?D?D?D?D?D?B?D@D?D?B?D@D?B@B?B@@@B?@?B?B?BAB?D?B?D?B@D@B?D?B?DAB?D?B@B?D@BBB@D@B@D@B@DBD@D@DBB@DBB@DBB@DBB@D@BBD@B@D@B@B@B@B@D@BBD@BBD@F@DBD?F@D@D@D@D@D@D@D?D@D?B@D@@?B@@@@@@B@@?B?BCBABC@EBCBCBCBEBCBCBCBCBABCBCBC@CBEBCBCBCBCDCBEDABCDCBCDABCBCDCBABCBABABCBABCBCDABCBABCDABCBABCBABCBCBCBABCBCBEBC@CBCBEBC@CBCBCBE@CBCBCBCDCBCBCDABCDCDADCBCDADCDCBADCDABCDABADAD?DAB?D@D?B@D@D@BBD@BBDBDBDBBBDDBBDBBBBD@B@D@D?B@D@B@B@B@DBBB@@BDBBBBBB@BBDBBDBBBDDBBBBBDBBBD@BBBBDBBBBBBBBBBBBB@@BBB@BBB@BBD@B@B@B@D@B@D@D@D@BBD@D@D@B@DBD@B@DBD@DBB@D@D@D@B@DBD@B?B@@?@?@A???A?AAA???A@A?A?C?C?A"
    },
    "summary": {
        "distance_km": "16.16",
        "duration": "01:36:44",
        "avg_pace": "5'59\"",
        "best_pace": "4'57\"",
        "calories_kcal": 945,
        "total_ascent_m": 39,
        "avg_cadence": 178,
        "avg_power_w": 183,
        "avg_hr": 140,
        "max_hr": 153
    },
    "laps": [
        {
            "lap_number": 1,
            "duration": "00:06:34",
            "distance_km": "1.00",
            "pace": "6'34\"",
            "avg_hr": 127,
            "avg_cadence": 176
        },
        {
            "lap_number": 2,
            "duration": "00:06:03",
            "distance_km": "1.00",
            "pace": "6'03\"",
            "avg_hr": 133,
            "avg_cadence": 180
        },
        {
            "lap_number": 3,
            "duration": "00:06:16",
            "distance_km": "1.00",
            "pace": "6'16\"",
            "avg_hr": 137,
            "avg_cadence": 178
        },
        {
            "lap_number": 4,
            "duration": "00:05:55",
            "distance_km": "1.00",
            "pace": "5'55\"",
            "avg_hr": 138,
            "avg_cadence": 178
        },
        {
            "lap_number": 5,
            "duration": "00:06:07",
            "distance_km": "1.00",
            "pace": "6'07\"",
            "avg_hr": 136,
            "avg_cadence": 178
        },
        {
            "lap_number": 6,
            "duration": "00:06:04",
            "distance_km": "1.00",
            "pace": "6'04\"",
            "avg_hr": 138,
            "avg_cadence": 178
        },
        {
            "lap_number": 7,
            "duration": "00:05:56",
            "distance_km": "1.00",
            "pace": "5'56\"",
            "avg_hr": 139,
            "avg_cadence": 178
        },
        {
            "lap_number": 8,
            "duration": "00:05:53",
            "distance_km": "1.00",
            "pace": "5'53\"",
            "avg_hr": 140,
            "avg_cadence": 178
        },
        {
            "lap_number": 9,
            "duration": "00:05:51",
            "distance_km": "1.00",
            "pace": "5'51\"",
            "avg_hr": 143,
            "avg_cadence": 178
        },
        {
            "lap_number": 10,
            "duration": "00:05:52",
            "distance_km": "1.00",
            "pace": "5'52\"",
            "avg_hr": 144,
            "avg_cadence": 178
        },
        {
            "lap_number": 11,
            "duration": "00:05:51",
            "distance_km": "1.00",
            "pace": "5'51\"",
            "avg_hr": 143,
            "avg_cadence": 178
        },
        {
            "lap_number": 12,
            "duration": "00:05:57",
            "distance_km": "1.00",
            "pace": "5'58\"",
            "avg_hr": 140,
            "avg_cadence": 178
        },
        {
            "lap_number": 13,
            "duration": "00:06:12",
            "distance_km": "1.00",
            "pace": "6'12\"",
            "avg_hr": 142,
            "avg_cadence": 178
        },
        {
            "lap_number": 14,
            "duration": "00:05:35",
            "distance_km": "1.00",
            "pace": "5'35\"",
            "avg_hr": 142,
            "avg_cadence": 178
        },
        {
            "lap_number": 15,
            "duration": "00:05:52",
            "distance_km": "1.00",
            "pace": "5'52\"",
            "avg_hr": 148,
            "avg_cadence": 178
        },
        {
            "lap_number": 16,
            "duration": "00:05:36",
            "distance_km": "1.00",
            "pace": "5'36\"",
            "avg_hr": 148,
            "avg_cadence": 178
        },
        {
            "lap_number": 17,
            "duration": "00:01:01",
            "distance_km": "0.16",
            "pace": "6'36\"",
            "avg_hr": 149,
            "avg_cadence": 168
        }
    ],
    "charts": {
        "pace": {
            "labels": [
                "0.0km",
                "0.1km",
                "0.2km",
                "0.3km",
                "0.4km",
                "0.5km",
                "0.6km",
                "0.7km",
                "0.8km",
                "0.9km",
                "1.0km",
                "1.2km",
                "1.3km",
                "1.4km",
                "1.5km",
                "1.6km",
                "1.7km",
                "1.8km",
                "1.9km",
                "2.0km",
                "2.1km",
                "2.2km",
                "2.3km",
                "2.4km",
                "2.5km",
                "2.6km",
                "2.7km",
                "2.8km",
                "2.9km",
                "3.0km",
                "3.1km",
                "3.2km",
                "3.4km",
                "3.5km",
                "3.6km",
                "3.7km",
                "3.8km",
                "3.9km",
                "4.0km",
                "4.1km",
                "4.2km",
                "4.3km",
                "4.4km",
                "4.5km",
                "4.7km",
                "4.8km",
                "4.9km",
                "5.0km",
                "5.1km",
                "5.2km",
                "5.3km",
                "5.4km",
                "5.5km",
                "5.6km",
                "5.7km",
                "5.8km",
                "5.9km",
                "6.0km",
                "6.2km",
                "6.3km",
                "6.4km",
                "6.5km",
                "6.6km",
                "6.7km",
                "6.8km",
                "6.9km",
                "7.0km",
                "7.1km",
                "7.2km",
                "7.4km",
                "7.5km",
                "7.6km",
                "7.7km",
                "7.8km",
                "7.9km",
                "8.0km",
                "8.1km",
                "8.2km",
                "8.3km",
                "8.5km",
                "8.6km",
                "8.7km",
                "8.8km",
                "8.9km",
                "9.0km",
                "9.1km",
                "9.2km",
                "9.4km",
                "9.5km",
                "9.6km",
                "9.7km",
                "9.8km",
                "9.9km",
                "10.0km",
                "10.1km",
                "10.2km",
                "10.4km",
                "10.5km",
                "10.6km",
                "10.7km",
                "10.8km",
                "10.9km",
                "11.0km",
                "11.1km",
                "11.2km",
                "11.3km",
                "11.4km",
                "11.5km",
                "11.7km",
                "11.8km",
                "11.9km",
                "12.0km",
                "12.1km",
                "12.2km",
                "12.3km",
                "12.4km",
                "12.5km",
                "12.6km",
                "12.7km",
                "12.8km",
                "12.9km",
                "13.0km",
                "13.2km",
                "13.3km",
                "13.4km",
                "13.5km",
                "13.6km",
                "13.7km",
                "13.8km",
                "14.0km",
                "14.1km",
                "14.2km",
                "14.3km",
                "14.4km",
                "14.5km",
                "14.6km",
                "14.8km",
                "14.9km",
                "15.0km",
                "15.1km",
                "15.2km",
                "15.3km",
                "15.4km",
                "15.5km",
                "15.6km",
                "15.8km",
                "15.9km",
                "16.0km",
                "16.1km",
                "16.2km"
            ],
            "data": [
                379.4871794871795,
                527.7777777777778,
                380.0,
                339.2857142857143,
                370.7317073170732,
                404.25531914893617,
                415.3005464480874,
                447.05882352941177,
                380.0,
                372.54901960784315,
                329.004329004329,
                372.54901960784315,
                361.9047619047619,
                365.38461538461536,
                337.77777777777777,
                358.4905660377359,
                340.8071748878924,
                436.7816091954023,
                370.7317073170732,
                395.83333333333337,
                391.7525773195876,
                368.9320388349514,
                383.83838383838383,
                376.23762376237624,
                413.4078212290503,
                340.8071748878924,
                358.4905660377359,
                367.14975845410623,
                404.25531914893617,
                355.14018691588785,
                376.23762376237624,
                356.80751173708916,
                330.4347826086957,
                348.6238532110092,
                351.85185185185185,
                347.0319634703196,
                395.83333333333337,
                350.2304147465438,
                345.45454545454544,
                370.7317073170732,
                372.54901960784315,
                380.0,
                365.38461538461536,
                378.1094527363184,
                361.9047619047619,
                372.54901960784315,
                358.4905660377359,
                368.9320388349514,
                348.6238532110092,
                362.7450980392157,
                345.45454545454544,
                361.9047619047619,
                406.4171122994652,
                361.9047619047619,
                350.2304147465438,
                361.9047619047619,
                376.23762376237624,
                355.14018691588785,
                355.14018691588785,
                358.4905660377359,
                365.38461538461536,
                342.34234234234236,
                351.85185185185185,
                358.4905660377359,
                374.384236453202,
                355.14018691588785,
                413.04347826086956,
                314.04958677685954,
                343.8914027149321,
                351.85185185185185,
                368.9320388349514,
                351.85185185185185,
                348.6238532110092,
                358.4905660377359,
                336.3636363636364,
                340.8071748878924,
                355.14018691588785,
                368.9320388349514,
                355.14018691588785,
                330.4347826086957,
                351.85185185185185,
                358.4905660377359,
                348.6238532110092,
                378.1094527363184,
                316.6666666666667,
                342.34234234234236,
                361.9047619047619,
                350.2304147465438,
                351.85185185185185,
                368.9320388349514,
                333.3333333333333,
                350.2304147465438,
                365.38461538461536,
                361.9047619047619,
                361.9047619047619,
                334.80176211453744,
                339.2857142857143,
                355.14018691588785,
                345.45454545454544,
                360.9756097560976,
                367.14975845410623,
                348.6238532110092,
                408.60215053763443,
                380.0,
                342.34234234234236,
                358.4905660377359,
                336.283185840708,
                365.38461538461536,
                342.34234234234236,
                355.14018691588785,
                350.2304147465438,
                348.6238532110092,
                391.7525773195876,
                365.38461538461536,
                370.7317073170732,
                361.9047619047619,
                356.80751173708916,
                361.9047619047619,
                380.0,
                372.54901960784315,
                408.60215053763443,
                327.5862068965517,
                319.327731092437,
                342.34234234234236,
                359.22330097087377,
                361.9047619047619,
                319.327731092437,
                345.45454545454544,
                336.283185840708,
                308.9430894308943,
                333.3333333333333,
                351.85185185185185,
                391.7525773195876,
                334.80176211453744,
                342.34234234234236,
                334.80176211453744,
                327.5862068965517,
                400.0,
                380.0,
                323.40425531914894,
                322.03389830508473,
                355.14018691588785,
                395.83333333333337,
                355.14018691588785,
                339.2857142857143,
                333.3333333333333,
                311.4754098360656,
                322.03389830508473,
                441.8604651162791,
                15.259021896696423
            ]
        },
        "elevation": {
            "labels": [
                "0.1km",
                "0.2km",
                "0.3km",
                "0.4km",
                "0.5km",
                "0.6km",
                "0.7km",
                "0.8km",
                "0.9km",
                "1.0km",
                "1.2km",
                "1.3km",
                "1.4km",
                "1.5km",
                "1.6km",
                "1.7km",
                "1.8km",
                "1.9km",
                "2.0km",
                "2.1km",
                "2.2km",
                "2.3km",
                "2.4km",
                "2.5km",
                "2.6km",
                "2.7km",
                "2.8km",
                "2.9km",
                "3.0km",
                "3.1km",
                "3.2km",
                "3.4km",
                "3.5km",
                "3.6km",
                "3.7km",
                "3.8km",
                "3.9km",
                "4.0km",
                "4.1km",
                "4.2km",
                "4.3km",
                "4.4km",
                "4.5km",
                "4.7km",
                "4.8km",
                "4.9km",
                "5.0km",
                "5.1km",
                "5.2km",
                "5.3km",
                "5.4km",
                "5.5km",
                "5.6km",
                "5.7km",
                "5.8km",
                "5.9km",
                "6.0km",
                "6.2km",
                "6.3km",
                "6.4km",
                "6.5km",
                "6.6km",
                "6.7km",
                "6.8km",
                "6.9km",
                "7.0km",
                "7.1km",
                "7.2km",
                "7.4km",
                "7.5km",
                "7.6km",
                "7.7km",
                "7.8km",
                "7.9km",
                "8.0km",
                "8.1km",
                "8.2km",
                "8.3km",
                "8.5km",
                "8.6km",
                "8.7km",
                "8.8km",
                "8.9km",
                "9.0km",
                "9.1km",
                "9.2km",
                "9.4km",
                "9.5km",
                "9.6km",
                "9.7km",
                "9.8km",
                "9.9km",
                "10.0km",
                "10.1km",
                "10.2km",
                "10.4km",
                "10.5km",
                "10.6km",
                "10.7km",
                "10.8km",
                "10.9km",
                "11.0km",
                "11.1km",
                "11.2km",
                "11.3km",
                "11.4km",
                "11.5km",
                "11.7km",
                "11.8km",
                "11.9km",
                "12.0km",
                "12.1km",
                "12.2km",
                "12.3km",
                "12.4km",
                "12.5km",
                "12.6km",
                "12.7km",
                "12.8km",
                "12.9km",
                "13.0km",
                "13.2km",
                "13.3km",
                "13.4km",
                "13.5km",
                "13.6km",
                "13.7km",
                "13.8km",
                "14.0km",
                "14.1km",
                "14.2km",
                "14.3km",
                "14.4km",
                "14.5km",
                "14.6km",
                "14.8km",
                "14.9km",
                "15.0km",
                "15.1km",
                "15.2km",
                "15.3km",
                "15.4km",
                "15.5km",
                "15.6km",
                "15.8km",
                "15.9km",
                "16.0km",
                "16.1km",
                "16.2km"
            ],
            "data": [
                40.87179487179487,
                42.0,
                41.76923076923077,
                41.743589743589745,
                42.0,
                42.56410256410256,
                43.41025641025641,
                42.02564102564103,
                40.794871794871796,
                39.43589743589744,
                37.92307692307692,
                37.0,
                37.0,
                35.61538461538461,
                34.0,
                33.717948717948715,
                31.974358974358974,
                31.0,
                31.615384615384617,
                32.58974358974359,
                33.69230769230769,
                34.15384615384615,
                35.0,
                34.81578947368421,
                33.05128205128205,
                31.641025641025642,
                33.53846153846154,
                34.87179487179487,
                35.46153846153846,
                36.282051282051285,
                35.61538461538461,
                35.0,
                34.205128205128204,
                31.82051282051282,
                30.0,
                30.0,
                30.0,
                30.0,
                30.0,
                29.102564102564102,
                29.153846153846153,
                29.153846153846153,
                29.0,
                29.205128205128204,
                29.71794871794872,
                29.41025641025641,
                28.512820512820515,
                29.0,
                28.973684210526315,
                28.153846153846153,
                28.641025641025642,
                29.46153846153846,
                32.38461538461539,
                29.71794871794872,
                27.102564102564102,
                27.0,
                27.153846153846153,
                27.0,
                27.0,
                27.0,
                27.0,
                27.025641025641026,
                27.076923076923077,
                27.28205128205128,
                27.743589743589745,
                27.0,
                27.794871794871796,
                27.46153846153846,
                28.0,
                27.615384615384617,
                27.0,
                27.0,
                27.153846153846153,
                27.0,
                27.128205128205128,
                27.641025641025642,
                27.05128205128205,
                27.0,
                27.28205128205128,
                27.28205128205128,
                27.307692307692307,
                27.0,
                27.0,
                27.0,
                27.0,
                27.0,
                27.0,
                27.0,
                27.0,
                27.0,
                27.0,
                27.205128205128204,
                27.205128205128204,
                27.0,
                27.153846153846153,
                27.666666666666668,
                27.53846153846154,
                27.153846153846153,
                27.0,
                27.0,
                27.0,
                27.0,
                27.0,
                27.0,
                27.0,
                27.0,
                27.025641025641026,
                27.0,
                27.0,
                27.384615384615383,
                27.641025641025642,
                27.58974358974359,
                27.666666666666668,
                28.0,
                29.0,
                29.333333333333332,
                31.435897435897434,
                34.48717948717949,
                36.12820512820513,
                37.0,
                35.87179487179487,
                35.17948717948718,
                35.743589743589745,
                32.578947368421055,
                30.0,
                28.076923076923077,
                28.0,
                28.0,
                28.102564102564102,
                29.794871794871796,
                32.38461538461539,
                33.0,
                33.0,
                32.41025641025641,
                32.07692307692308,
                33.56410256410256,
                35.8974358974359,
                38.38461538461539,
                38.53846153846154,
                38.0,
                39.64102564102564,
                40.92307692307692,
                40.76923076923077,
                37.84615384615385,
                37.15384615384615,
                37.0,
                37.282051282051285,
                1004.025641025641,
                36.0
            ]
        },
        "hr": {
            "labels": [
                "0.1km",
                "0.2km",
                "0.3km",
                "0.4km",
                "0.5km",
                "0.6km",
                "0.7km",
                "0.8km",
                "0.9km",
                "1.0km",
                "1.2km",
                "1.3km",
                "1.4km",
                "1.5km",
                "1.6km",
                "1.7km",
                "1.8km",
                "1.9km",
                "2.0km",
                "2.1km",
                "2.2km",
                "2.3km",
                "2.4km",
                "2.5km",
                "2.6km",
                "2.7km",
                "2.8km",
                "2.9km",
                "3.0km",
                "3.1km",
                "3.2km",
                "3.4km",
                "3.5km",
                "3.6km",
                "3.7km",
                "3.8km",
                "3.9km",
                "4.0km",
                "4.1km",
                "4.2km",
                "4.3km",
                "4.4km",
                "4.5km",
                "4.7km",
                "4.8km",
                "4.9km",
                "5.0km",
                "5.1km",
                "5.2km",
                "5.3km",
                "5.4km",
                "5.5km",
                "5.6km",
                "5.7km",
                "5.8km",
                "5.9km",
                "6.0km",
                "6.2km",
                "6.3km",
                "6.4km",
                "6.5km",
                "6.6km",
                "6.7km",
                "6.8km",
                "6.9km",
                "7.0km",
                "7.1km",
                "7.2km",
                "7.4km",
                "7.5km",
                "7.6km",
                "7.7km",
                "7.8km",
                "7.9km",
                "8.0km",
                "8.1km",
                "8.2km",
                "8.3km",
                "8.5km",
                "8.6km",
                "8.7km",
                "8.8km",
                "8.9km",
                "9.0km",
                "9.1km",
                "9.2km",
                "9.4km",
                "9.5km",
                "9.6km",
                "9.7km",
                "9.8km",
                "9.9km",
                "10.0km",
                "10.1km",
                "10.2km",
                "10.4km",
                "10.5km",
                "10.6km",
                "10.7km",
                "10.8km",
                "10.9km",
                "11.0km",
                "11.1km",
                "11.2km",
                "11.3km",
                "11.4km",
                "11.5km",
                "11.7km",
                "11.8km",
                "11.9km",
                "12.0km",
                "12.1km",
                "12.2km",
                "12.3km",
                "12.4km",
                "12.5km",
                "12.6km",
                "12.7km",
                "12.8km",
                "12.9km",
                "13.0km",
                "13.2km",
                "13.3km",
                "13.4km",
                "13.5km",
                "13.6km",
                "13.7km",
                "13.8km",
                "14.0km",
                "14.1km",
                "14.2km",
                "14.3km",
                "14.4km",
                "14.5km",
                "14.6km",
                "14.8km",
                "14.9km",
                "15.0km",
                "15.1km",
                "15.2km",
                "15.3km",
                "15.4km",
                "15.5km",
                "15.6km",
                "15.8km",
                "15.9km",
                "16.0km",
                "16.1km",
                "16.2km"
            ],
            "data": [
                122.8974358974359,
                129.17948717948718,
                131.74358974358975,
                128.0,
                127.56410256410257,
                128.05128205128204,
                129.3846153846154,
                127.0,
                128.82051282051282,
                127.92307692307692,
                127.66666666666667,
                135.25641025641025,
                132.17948717948718,
                134.94871794871796,
                134.94871794871796,
                134.94871794871796,
                133.84615384615384,
                130.48717948717947,
                133.56410256410257,
                137.33333333333334,
                139.15384615384616,
                139.74358974358975,
                138.76923076923077,
                135.78947368421052,
                135.2051282051282,
                135.12820512820514,
                135.69230769230768,
                136.46153846153845,
                137.89743589743588,
                138.25641025641025,
                140.5897435897436,
                140.17948717948718,
                136.97435897435898,
                136.71794871794873,
                140.05128205128204,
                135.53846153846155,
                138.84615384615384,
                137.0,
                136.07692307692307,
                136.5897435897436,
                134.94871794871796,
                133.89743589743588,
                131.4102564102564,
                134.87179487179486,
                139.4102564102564,
                137.33333333333334,
                135.48717948717947,
                136.05128205128204,
                137.5,
                139.97435897435898,
                138.10256410256412,
                142.0,
                144.97435897435898,
                138.35897435897436,
                133.46153846153845,
                134.6153846153846,
                136.6153846153846,
                139.12820512820514,
                137.10256410256412,
                138.17948717948718,
                137.89743589743588,
                140.87179487179486,
                139.05128205128204,
                139.51282051282053,
                139.46153846153845,
                137.56410256410257,
                136.92307692307693,
                136.3846153846154,
                139.05128205128204,
                141.07692307692307,
                140.84615384615384,
                141.12820512820514,
                141.33333333333334,
                141.55263157894737,
                144.51282051282053,
                143.69230769230768,
                141.17948717948718,
                143.66666666666666,
                143.97435897435898,
                144.28205128205127,
                144.56410256410257,
                142.3846153846154,
                143.5897435897436,
                143.25641025641025,
                145.25641025641025,
                145.82051282051282,
                143.87179487179486,
                142.53846153846155,
                143.66666666666666,
                145.6153846153846,
                145.25641025641025,
                143.48717948717947,
                141.97435897435898,
                142.7948717948718,
                144.74358974358975,
                144.7948717948718,
                143.89743589743588,
                143.74358974358975,
                141.8421052631579,
                143.76923076923077,
                140.97435897435898,
                141.87179487179486,
                139.5897435897436,
                140.28205128205127,
                139.64102564102564,
                139.28205128205127,
                138.64102564102564,
                139.02564102564102,
                141.69230769230768,
                142.92307692307693,
                141.53846153846155,
                140.0,
                136.89743589743588,
                138.12820512820514,
                140.84615384615384,
                140.02564102564102,
                146.17948717948718,
                146.74358974358975,
                147.25641025641025,
                144.76923076923077,
                142.15384615384616,
                141.87179487179486,
                141.66666666666666,
                139.10526315789474,
                139.33333333333334,
                138.51282051282053,
                141.89743589743588,
                144.51282051282053,
                147.10256410256412,
                148.53846153846155,
                148.69230769230768,
                147.74358974358975,
                145.46153846153845,
                147.05128205128204,
                145.6153846153846,
                146.92307692307693,
                149.35897435897436,
                151.15384615384616,
                151.97435897435898,
                149.7948717948718,
                149.17948717948718,
                149.07692307692307,
                148.87179487179486,
                145.84615384615384,
                145.84615384615384,
                146.87179487179486,
                148.02564102564102,
                149.5897435897436,
                145
            ]
        }
    },
    "photos": [
        {
            "url": "https://picsum.photos/seed/1744062859000_a/600/400"
        },
        {
            "url": "https://picsum.photos/seed/1744062859000_b/600/400"
        }
    ]
}