{
    "run_id": 1755813628000,
    "start_time": "2025-08-21T22:00:28+00:00",
    "weather": null,
    "route": {
        "encoded_polyline": "g`zkC_rjrTBB@BBBBBBBD@B@B@D@BBB@D@B@BBB@BBB@@@BBB@B@B@B@B@BB@@BBB@B@B@B@B?D@BAD?D?B?D@B?B@B@B@B@@BB@@@BBBBBBBBB@BBB@B@@@B@B@B@B?B@B@B@B@B@B@B@@@B@B@BBB@@@B@B@B@B@B?B?D?BADABABC@C@CBC?C@C@C?C@C?C@C@C?C@E@C@C@C@E@C@CBC@E@C@C@E@C@C@E@C@E@C@C?E@C@C@E@C?A@CBE@C@C?C@E@C@C?A@C@C@C@C@C@C@C?C@C@C@C@EBC@C@C@E@A@C????AB?BAB?BADABABADABAB?BAB?B?B?B@B@@@B@@@@B@@?BC@ABC@C@EBE@C@EBE@E@CBE@C@C@EBC@C@E@C@CBC@EBCBC@CBC@C@CBC@C@EBC@CBC@E@CBC@C@E@C@C@C@EBC@C@C@E@C@C@E@C@E@C@E@C@E@C@E@C@E@E@C@E@C@C@E@C?C@C@E@C@C@E@C@C@E@C@E@E@C@E?C@E@E?C@E@C?E@C@E@C@E@C?C@C@E@C?C@C@C@C@C@C@A@C@CBA@C@A@C@C@C@A@C@CBC@C@C@C@C@C@C@C?E@C@C@C@C@C@EBC@C?E@C@C@E@C@C?E@C@C@CBC@E@CBCBABC@CBA@C@A@C@C@C@C@C@CBC@EBC@EBCBE@C@EBC@E@C@E?C?C?C?E?C?C@E?C@E@C?E@E@E?E@E?E?E@E?C@E@C?C@E@C@C@C@C@CBC@C@CBC@CBA@C@E@C?C@E?C@C?C@C?C@C?C@C?C@C@E@C@C@C@E@C?C@E?C@C?E@C?E@C@E@C@E@C?EBC@C@E@C@C@E@C@E@C@E@C@E@C@EBC@CBEBC@EBC@C@E@C@E@CBE@C@CBC@CBC@CBC@CBC@C@CBC@E@C@C?C@E@C?C@C@C@C@C@E@A@C@C@C@C@A@C@CBC@C@ABC@C@C@C@E?C@E@E@E@EBG@C@E@C@C?E@C@C@C@E@C@E@C@EBE@E@E@C@C@C@C@CBC@E@C@CBE@C@E?C@C@E@C@E@C?E@C@C@E@C?E@C@C@E@C?E?C?EAC@C?C@E@C@C@C@E@C@CBC@CBCBABAB?B?D?B@B@B?B@D@B@B@B@D@B@B@B@B@B@B@B?B@B@B@B@B@B@BBB@B@DBB@B@D@B?B?@?BA?C?AAEACACCCCCCEACCCACCCACCCACCCACACCCACCACCACCCCCCAACCCACCAACACACAE?C?C?C?C?E@C?E@C@C@E@C@C?C@C@C@C@C@C@C@C@C@E@CBC@C@E@C@C?E@E?E?E?E?E?E?E?E?E?E?C?E?C@E@C?C@C@E@C@C?E@C@C@E?C@C@C@CBC@C@E@C@C@C@E@C@E@C@E@C@EBC@E@CBC@EBC@CBE@C@C@E@E@C@E@E@C@E@E@C@E@E@C@E@C@E@C@E@C@E@C@E@C@E@C@E@CBC@E@C@C@C@C@C@CBC@C@C@C@CBE@C@C@C@C@EBC@C@E@CBC@C@CBC@C@C@CBC@C@C@C@E@C?E@E?E?C@E?E@C@E?C@E?C@E@C?E@C@EBC@C@E@C@C@C@C?C@E@C?C@E@C@C?E@C@C@E?C@C?E?C@E@C@E@C@C@C@E@C@E@E@C@E@C@C@C@C@C@CBC@C@CBCBABCB?BADAD?B?D?BAD?BAB?BAD?B?BAB?BAB?BAD?B?BAD?BAD?D?BAD?D?B?DAD?B?D?D?BAD?B?D?B?BAD?B?D?B?D?DAB?D?B?DAB?B?D?B?B?D?B?D?D?B?DAB?B?DAB?D?B?D?B?D?B?D?B?D?BAD?B?D?B?B?B@D?B?B?B?D?D?B?D?B?D?BAD?B?D?D?B?DAB?D?BAD?D?BAD?BAB?DABABABAB?BA@AB?BA@?BAD?BAB?DADADAD?D?FAD@B?D@D?B@D@B@D?D@B@D@D@D@B@D@D@D@B?D@D?D@B?D?D@B?D?D@D?D?D@B?D?D@B?D@B?D?D?B?D@B?D?B?D@D?B?D?B@D?B?D@B?D?D@B?D?D@B?D@B?D@B@D?D@B?D@B?B@D?B?B?B?D?B?D?B?D?B?D?B?D?D@B?D?B@D?B?D?B@B?D@B?D?B@B?D?B?B?D@B@B@B@@BB@?B@B@D@B@D?B@D?B?D?DAB?D?D?B?D@D?B@D@D@B?D@B?D@D?B@D?D?B?D?D?B?D?BAD?B?DAB?B?DAD@B?D?D?B@D@D?D?D?DAD?B?D?DAD?B?D?D?B?D?D?D?B?D?D?D?D?D?D?D?B?D?D?D?D?D?B?D?B?D?D?B?D?D?BAD?B?D?D?DAD?B?DAB?D?DAB?DAD?D?B?D?D?BAD?B?D?B?D?B?D?B@D?B?D?B?DAD?BAD?D?D?BAD?B?D?D?B@D?D?B?D?D?D?B?D?D?D?D?D?D?D?DAD?D?B?D?D?B?DAB?D?D?B?D?B?D?D?B?D@BBB@BD@B@D?D?B?D?D?B?D?DAB?D?B?D?D?B?DAB?D?B?D?B?D?D?D?B?D?D?DABADABAD?DABAD?BAD?BAD?B?D?D?B?D?B?DAB?D?BAD?B?D?B@D?B@D?B?BABC@CBC@C@E@E@E@C?EBE@C@E@C@E@C@E@C@C@C@EBC@C@E@C@E@C@E@C@E@C@E@C@E?C@E@C@E@C@E@C@E@C@E@CBC@E@CBC@CBCBCBC@ADCBABCBABCBADABCBABC@CBCBC@C@CBE@C@C@EBC@E@E@C@E@C@E@C@E@C@EBE@E@C@E@E@C@E@C@E@E@C@E@C@E@C@E@C@E@C@EBC@E@C@E@C@E@CBE@C@E@C@E@C@E@C?E@E@C@E?CBE@C@C@EBC@C@EBC@E@E@C@E@C@E@C@E@C@C@EBC@E@C@E@C@E?C@E@C?E@E?C@E?C@E?E?CAEACACCAC?C?C@CBCBCBADCDADADADCBADADCBADABADABCDABADABADADABADABADABADABADABABADABADABADABCBABC@CBC@C?C?E?C?C?EAC?C?EAC?C?CAE?C?CAC?CAE?CAC?C?EAC?CAEACACAEACACAEAC?CAC?EACAC?CAE?CAC?E?EAC?E?C?EAE?C?E?E?E?CAE?E?C?E?E?C?C?C?C?C?CAC@E?C?E?C?E?E?CAC?EAE?C?EAG?ECEAECEACAE?C?CAA?C?C?C?C?C?EAC?E?C?EAC?EAE?CACACACACCCCACAAC?A?AB?BAD?D@D?B@D@BBBBBB@B?D@B?B@B?D?B?B?B@D?B?B@D?B?B@B?B@B?B@B@B?BBD@BBD@BBB@D@B@B@B@B?B@D@B@B?D@B?B@D@D?BBD@DBB@DBB@D?D@B?D@B?D?D@D?D?D?D?D?D?D?D?D?D?D?F?D?D?D?DAD?D?D@B?D?DAD?DAD?DAD?B?DAD?B?DAB?D?DAB?D?B?DAB?B@B?B@B@@@@D@B?DABADADADAFCBADADABABADABABABADABABADABABADABABADABCDABABCDABCDABCBADABABADABADABABADABADABADABCBABABADAD?B?D@D?D?D?B?DAD?BADADABADCBABADCBABABADABABCDABADABADABADABABADABABADABADABADABADABADABADADABADABADABABADABADABADABADABADABADABADABADABCDADABADADABADADABADABADADABABADABADABADABADCBADADAB?BADABADABAD?BABADCBABADABADABADABADCBADADABADCBADADABADABADCBADABADABADCBABADABABADABABADABCBADABADABABCDABABADABABADCBABADABAB?DABABADABADAB?DABABADABADABABADABABADABADABADABABCDABABCBADCBABCDABCBADAD?BAD?D?D?D?B?D?D@D?D?D?D?B@D?D?D?D?D?D?B?D@D?D?D?D?D?D?D?D?D?B@D?DAD?B?D?DAB?DADAB?DADABADADABADABADABADADABADABADABADABAD?DABADABADADABADABADCBADADABADABADADADABADABADABADADABADABCDABADABADADABADABADCBABADABCBABADCBABCBABCBABCBCBCBCBCBCBCBEBCBCBCBABCBCDABCDABCBADCBABADCBADABCBADCBADCBCDABCBCBADCBCBABCBABABADAB?DAD?BADADAB?DABADABAB?DABABADABADABABADABCBABCBABCBC@CBCBCBABCBABABCDABADABCDADCBADABCDABABCDABCBCBCBCBC@CBC@C@CBC@C@CBC@ABCBC@CBE@CBC@CBCBABCBCBCBABCBADAB?DAD?BAD@D?D?D@D@B@D@D@D@B@D@D@B@D@D?B@D?B@D?B?DAB?DCBABABCDABAD?D?D?DAB?D?DADADAB?DCBADABABCBADABABADCBADABADABADCBADADABCDABADABCDABADABADCBADABADABABADABCDABCBCBABCBADCBABADABAD?BADAB?DABADABADABADADABADADABAD?BADABADABADABABADCBADABADCDABADADADABADAD?BADADABADADAB?DADABADABADADABADADABADADAD?DAB?DADAD?BADADABAD?DABADADABADADABCDABADABADCBADABABADABADABCDABADABCBADCBABCDABABCBADCBABCBABCBCDC@CBCBC@E@C@C@E?C?C?E?CAC?EAC?E?CAC?E?C@E?C?E@C?E?E?CAEACACAEACACCCACACAEACACACACACCCACACACACACACACACACACAEACACAECCAEACACCEACACACCEACCCACCCCCCCACCACCACCAACACAEACACAEACAEAEACAEACAEACCCAEACACCECCCCCCCCCECCCCACCCAECCACAE?E?E?E?E?CAE?E?CAC?EAC?CAC?EAE?CAEACAECCACCCACCCAEACACAEACCCAEACACCEACACCEACACAECCACAECCCCACCCACCCACACCCAEACACAECCACAECCACCCACCCACACCCAEAC?CAEAC?EAC?EAC?EACAE?CACACAEACCCCCCCCCCAECACCCCCACCAAEACACAE?CAEAC?CACACACCCACAEACAC?EAEACAEACAEAEACAEACACAEACACACAE?CAC?E?CAC?EAC?CAEAC?E?EAC?E?CAEAC?CACCCAEACCCACCCCCCCACCCCCACACACCCACCCCCACCAACACCEACACCCAAACACACACAC?CACAC?EAC?CAC?C?C?CAEACAEACAEACACCCAACCACCCACACAEACACACACCCACCCCECCCCCCACCCCCACCCCACCCCACCCACCCAEACCCACACACAC?CACACACACAAAAC?C@E?C@E@C?E@C@E@C@C@E@C@C@C@C@E@C@C@E@C@E@CBE?C@E@C@E@C?E@C@E@C@E@E@C@E@C@E@C@E@CAC?CCCAAECCCEACAEAE?CAE?C?E?C@C@ABABCDABADABADABAB?DABABABADABCBABADABABADABCBABABABABABABABABAB?B?BABABCBABADCBCBCBA@C@C?C?C?CACCCACCCACCEACACCCACAEACAC?CACACACCCAACCCCCAACCCCCCAACACACCCAACCA?EAC?EACAE?EACAEAEAC?EACAE?CAE?CACACCCAEACACAEACAE?EACAEAEACAEACCCACCCCCECCAEAE?E?C@E@E@CDCBABCDABADABADABABABABCBADCDAFCD"
    },
    "summary": {
        "distance_km": "8.01",
        "duration": "00:48:47",
        "avg_pace": "6'05\"",
        "best_pace": "4'59\"",
        "calories_kcal": 482,
        "total_ascent_m": 19,
        "avg_cadence": 178,
        "avg_power_w": 179,
        "avg_hr": 137,
        "max_hr": 150
    },
    "laps": [
        {
            "lap_number": 1,
            "duration": "00:06:32",
            "distance_km": "1.00",
            "pace": "6'32\"",
            "avg_hr": 120,
            "avg_cadence": 178
        },
        {
            "lap_number": 2,
            "duration": "00:06:19",
            "distance_km": "1.00",
            "pace": "6'19\"",
            "avg_hr": 131,
            "avg_cadence": 178
        },
        {
            "lap_number": 3,
            "duration": "00:06:01",
            "distance_km": "1.00",
            "pace": "6'01\"",
            "avg_hr": 136,
            "avg_cadence": 180
        },
        {
            "lap_number": 4,
            "duration": "00:05:56",
            "distance_km": "1.00",
            "pace": "5'56\"",
            "avg_hr": 138,
            "avg_cadence": 178
        },
        {
            "lap_number": 5,
            "duration": "00:05:56",
            "distance_km": "1.00",
            "pace": "5'56\"",
            "avg_hr": 140,
            "avg_cadence": 178
        },
        {
            "lap_number": 6,
            "duration": "00:05:53",
            "distance_km": "1.00",
            "pace": "5'53\"",
            "avg_hr": 143,
            "avg_cadence": 178
        },
        {
            "lap_number": 7,
            "duration": "00:05:52",
            "distance_km": "1.00",
            "pace": "5'52\"",
            "avg_hr": 144,
            "avg_cadence": 180
        },
        {
            "lap_number": 8,
            "duration": "00:06:11",
            "distance_km": "1.00",
            "pace": "6'11\"",
            "avg_hr": 147,
            "avg_cadence": 180
        },
        {
            "lap_number": 9,
            "duration": "00:00:03",
            "distance_km": "0.01",
            "pace": "8'21\"",
            "avg_hr": 146,
            "avg_cadence": 178
        }
    ],
    "charts": {
        "pace": {
            "labels": [
                "0.1km",
                "0.1km",
                "0.2km",
                "0.2km",
                "0.3km",
                "0.3km",
                "0.4km",
                "0.4km",
                "0.5km",
                "0.5km",
                "0.6km",
                "0.6km",
                "0.7km",
                "0.7km",
                "0.8km",
                "0.8km",
                "0.9km",
                "0.9km",
                "1.0km",
                "1.0km",
                "1.1km",
                "1.1km",
                "1.2km",
                "1.2km",
                "1.3km",
                "1.3km",
                "1.4km",
                "1.4km",
                "1.5km",
                "1.5km",
                "1.6km",
                "1.6km",
                "1.7km",
                "1.7km",
                "1.8km",
                "1.9km",
                "1.9km",
                "2.0km",
                "2.0km",
                "2.1km",
                "2.1km",
                "2.2km",
                "2.2km",
                "2.3km",
                "2.3km",
                "2.4km",
                "2.4km",
                "2.5km",
                "2.5km",
                "2.6km",
                "2.7km",
                "2.7km",
                "2.8km",
                "2.8km",
                "2.9km",
                "2.9km",
                "3.0km",
                "3.0km",
                "3.1km",
                "3.1km",
                "3.2km",
                "3.3km",
                "3.3km",
                "3.4km",
                "3.4km",
                "3.5km",
                "3.5km",
                "3.6km",
                "3.6km",
                "3.7km",
                "3.8km",
                "3.8km",
                "3.9km",
                "3.9km",
                "4.0km",
                "4.0km",
                "4.1km",
                "4.1km",
                "4.2km",
                "4.2km",
                "4.3km",
                "4.4km",
                "4.4km",
                "4.5km",
                "4.5km",
                "4.6km",
                "4.6km",
                "4.7km",
                "4.7km",
                "4.8km",
                "4.9km",
                "4.9km",
                "5.0km",
                "5.0km",
                "5.1km",
                "5.1km",
                "5.2km",
                "5.2km",
                "5.3km",
                "5.4km",
                "5.4km",
                "5.5km",
                "5.5km",
                "5.6km",
                "5.6km",
                "5.7km",
                "5.8km",
                "5.8km",
                "5.9km",
                "5.9km",
                "6.0km",
                "6.0km",
                "6.1km",
                "6.1km",
                "6.2km",
                "6.2km",
                "6.3km",
                "6.4km",
                "6.4km",
                "6.5km",
                "6.5km",
                "6.6km",
                "6.6km",
                "6.7km",
                "6.7km",
                "6.8km",
                "6.9km",
                "6.9km",
                "7.0km",
                "7.0km",
                "7.1km",
                "7.1km",
                "7.2km",
                "7.2km",
                "7.3km",
                "7.4km",
                "7.4km",
                "7.5km",
                "7.5km",
                "7.6km",
                "7.6km",
                "7.7km",
                "7.7km",
                "7.8km",
                "7.8km",
                "7.9km",
                "7.9km",
                "8.0km"
            ],
            "data": [
                366.25341073488744,
                376.8570125156197,
                391.7267314321529,
                397.14058776806985,
                404.5996592844976,
                401.0427110487267,
                419.42790034393084,
                439.70285344009636,
                386.9370066553165,
                364.31863307648877,
                370.18996590355573,
                368.867576540022,
                370.3635117868188,
                389.90355017443045,
                401.3243704223941,
                401.9292604501607,
                382.45536343324136,
                364.6507557386913,
                368.29699469652314,
                381.74073776420477,
                376.18026558326756,
                354.8483490213656,
                366.38088957279984,
                374.81961805880917,
                374.1556881510803,
                369.2762186115214,
                371.9407870267053,
                375.9993667379085,
                377.23037458976194,
                381.14840012959047,
                380.72337441138166,
                382.34338259190577,
                367.3634326439146,
                377.1712158808933,
                372.4256079848049,
                364.45140951582636,
                371.2532728906953,
                375.4810851403362,
                371.73339281067626,
                378.8180875667917,
                383.8845275341176,
                384.3430767674724,
                373.46877801015825,
                365.51711533892575,
                360.0667070952092,
                357.6409999642359,
                358.8988981803826,
                351.8192759929636,
                329.1747588794891,
                324.54361054766736,
                331.28748779467145,
                339.6681442230941,
                348.5717273471948,
                355.52561655626664,
                362.36479263674744,
                356.0556158872015,
                354.1274486049242,
                357.1811265492732,
                363.4315204157657,
                363.58069577863677,
                361.16077071708474,
                358.05718173192247,
                358.152686145146,
                356.2205004898031,
                354.3123543123543,
                357.53870356466086,
                359.85461873403153,
                358.4026559523137,
                352.9204164460914,
                351.08661306744364,
                351.38334073087736,
                354.70426531879053,
                354.59106785100073,
                350.5729099396645,
                355.1136363636365,
                362.43702656663413,
                366.22976098689276,
                360.99128206053825,
                361.7683235655886,
                368.95353127366633,
                370.844226882498,
                376.3076691502973,
                376.2674271229404,
                358.15336126929543,
                304.19468459814277,
                309.7509602279768,
                340.06087089589033,
                354.16705500773577,
                360.8610143803115,
                358.3844031107766,
                358.94432584588054,
                357.7945543668826,
                353.8382605311112,
                357.1160063153146,
                355.827565961535,
                354.7105561861522,
                358.93076414470573,
                361.70289724020677,
                359.1954022988506,
                354.20667027087495,
                351.6916367728775,
                351.1914168817713,
                349.4381402534347,
                348.86357689825394,
                348.37136387388955,
                345.3917469550991,
                352.7336860670194,
                362.33956938802754,
                358.0764135066423,
                358.3844031107767,
                358.2674938245998,
                355.14516558643356,
                352.4788072117164,
                351.3638465094776,
                350.39156257117315,
                351.33948177426436,
                350.8059304665719,
                347.5118154017236,
                345.1846738004834,
                345.6493660062943,
                347.27648417287423,
                352.82080231450453,
                357.8558782536633,
                361.4740913445028,
                363.4117091252681,
                364.84436507479313,
                359.74458134724347,
                351.9365773241706,
                351.48149449931464,
                352.67148651031573,
                355.39926301416,
                359.6410782039526,
                360.75036075036087,
                361.3747456111989,
                365.4636820465966,
                371.871629913354,
                380.70811709780196,
                369.7199371476106,
                366.36075543587765,
                366.57598734348164,
                365.945144822791,
                358.42936253337865,
                374.709107403463,
                384.7633705271259,
                379.5570569145807,
                375.0345426552447,
                365.4770389050309,
                342.43489231323775
            ]
        },
        "elevation": {
            "labels": [
                "0.1km",
                "0.1km",
                "0.2km",
                "0.2km",
                "0.3km",
                "0.3km",
                "0.4km",
                "0.4km",
                "0.5km",
                "0.5km",
                "0.6km",
                "0.6km",
                "0.7km",
                "0.7km",
                "0.8km",
                "0.8km",
                "0.9km",
                "0.9km",
                "1.0km",
                "1.0km",
                "1.1km",
                "1.1km",
                "1.2km",
                "1.2km",
                "1.3km",
                "1.3km",
                "1.4km",
                "1.4km",
                "1.5km",
                "1.5km",
                "1.6km",
                "1.6km",
                "1.7km",
                "1.7km",
                "1.8km",
                "1.9km",
                "1.9km",
                "2.0km",
                "2.0km",
                "2.1km",
                "2.1km",
                "2.2km",
                "2.2km",
                "2.3km",
                "2.3km",
                "2.4km",
                "2.4km",
                "2.5km",
                "2.5km",
                "2.6km",
                "2.7km",
                "2.7km",
                "2.8km",
                "2.8km",
                "2.9km",
                "2.9km",
                "3.0km",
                "3.0km",
                "3.1km",
                "3.1km",
                "3.2km",
                "3.3km",
                "3.3km",
                "3.4km",
                "3.4km",
                "3.5km",
                "3.5km",
                "3.6km",
                "3.6km",
                "3.7km",
                "3.8km",
                "3.8km",
                "3.9km",
                "3.9km",
                "4.0km",
                "4.0km",
                "4.1km",
                "4.1km",
                "4.2km",
                "4.2km",
                "4.3km",
                "4.4km",
                "4.4km",
                "4.5km",
                "4.5km",
                "4.6km",
                "4.6km",
                "4.7km",
                "4.7km",
                "4.8km",
                "4.9km",
                "4.9km",
                "5.0km",
                "5.0km",
                "5.1km",
                "5.1km",
                "5.2km",
                "5.2km",
                "5.3km",
                "5.4km",
                "5.4km",
                "5.5km",
                "5.5km",
                "5.6km",
                "5.6km",
                "5.7km",
                "5.8km",
                "5.8km",
                "5.9km",
                "5.9km",
                "6.0km",
                "6.0km",
                "6.1km",
                "6.1km",
                "6.2km",
                "6.2km",
                "6.3km",
                "6.4km",
                "6.4km",
                "6.5km",
                "6.5km",
                "6.6km",
                "6.6km",
                "6.7km",
                "6.7km",
                "6.8km",
                "6.9km",
                "6.9km",
                "7.0km",
                "7.0km",
                "7.1km",
                "7.1km",
                "7.2km",
                "7.2km",
                "7.3km",
                "7.4km",
                "7.4km",
                "7.5km",
                "7.5km",
                "7.6km",
                "7.6km",
                "7.7km",
                "7.7km",
                "7.8km",
                "7.8km",
                "7.9km",
                "7.9km",
                "8.0km"
            ],
            "data": [
                18.0,
                18.0,
                18.0,
                17.4,
                15.842105263157896,
                14.7,
                13.45,
                13.0,
                13.05,
                12.25,
                11.052631578947368,
                9.8,
                9.0,
                9.0,
                9.0,
                9.0,
                9.0,
                9.0,
                8.55,
                9.0,
                9.35,
                9.473684210526315,
                9.0,
                9.0,
                9.0,
                9.0,
                9.0,
                9.0,
                8.6,
                8.0,
                8.947368421052632,
                8.9,
                8.0,
                8.052631578947368,
                8.0,
                8.05,
                8.052631578947368,
                8.75,
                8.3,
                8.0,
                8.0,
                8.842105263157896,
                8.45,
                9.0,
                9.0,
                9.0,
                9.0,
                8.157894736842104,
                8.0,
                8.0,
                8.0,
                8.55,
                9.0,
                9.526315789473685,
                10.0,
                10.0,
                10.0,
                10.0,
                9.85,
                9.421052631578947,
                10.0,
                9.65,
                9.631578947368421,
                9.2,
                9.0,
                9.0,
                9.0,
                9.0,
                8.55,
                8.5,
                8.578947368421053,
                8.95,
                9.0,
                9.0,
                8.55,
                9.0,
                9.0,
                9.1,
                9.7,
                9.31578947368421,
                9.3,
                9.0,
                9.0,
                9.0,
                9.0,
                8.6,
                8.0,
                8.0,
                8.0,
                8.0,
                7.947368421052632,
                7.35,
                8.0,
                8.0,
                7.5,
                7.8,
                8.526315789473685,
                9.75,
                10.0,
                9.578947368421053,
                8.1,
                7.35,
                7.315789473684211,
                7.0,
                7.05,
                7.0,
                7.35,
                8.578947368421053,
                9.3,
                9.0,
                9.0,
                7.85,
                7.0,
                7.0,
                7.0,
                7.0,
                7.0,
                7.0,
                7.0,
                7.0,
                7.0,
                6.95,
                6.315789473684211,
                6.75,
                6.8,
                7.0,
                7.0,
                7.0,
                7.0,
                7.0,
                7.421052631578948,
                8.0,
                8.0,
                8.894736842105264,
                9.6,
                10.6,
                12.157894736842104,
                13.8,
                14.0,
                13.0,
                11.85,
                11.5,
                12.473684210526315,
                13.7,
                14.95,
                15.0,
                15.0,
                15.0
            ]
        },
        "hr": {
            "labels": [
                "0.1km",
                "0.1km",
                "0.2km",
                "0.2km",
                "0.3km",
                "0.3km",
                "0.4km",
                "0.4km",
                "0.5km",
                "0.5km",
                "0.6km",
                "0.6km",
                "0.7km",
                "0.7km",
                "0.8km",
                "0.8km",
                "0.9km",
                "0.9km",
                "1.0km",
                "1.0km",
                "1.1km",
                "1.1km",
                "1.2km",
                "1.2km",
                "1.3km",
                "1.3km",
                "1.4km",
                "1.4km",
                "1.5km",
                "1.5km",
                "1.6km",
                "1.6km",
                "1.7km",
                "1.7km",
                "1.8km",
                "1.9km",
                "1.9km",
                "2.0km",
                "2.0km",
                "2.1km",
                "2.1km",
                "2.2km",
                "2.2km",
                "2.3km",
                "2.3km",
                "2.4km",
                "2.4km",
                "2.5km",
                "2.5km",
                "2.6km",
                "2.7km",
                "2.7km",
                "2.8km",
                "2.8km",
                "2.9km",
                "2.9km",
                "3.0km",
                "3.0km",
                "3.1km",
                "3.1km",
                "3.2km",
                "3.3km",
                "3.3km",
                "3.4km",
                "3.4km",
                "3.5km",
                "3.5km",
                "3.6km",
                "3.6km",
                "3.7km",
                "3.8km",
                "3.8km",
                "3.9km",
                "3.9km",
                "4.0km",
                "4.0km",
                "4.1km",
                "4.1km",
                "4.2km",
                "4.2km",
                "4.3km",
                "4.4km",
                "4.4km",
                "4.5km",
                "4.5km",
                "4.6km",
                "4.6km",
                "4.7km",
                "4.7km",
                "4.8km",
                "4.9km",
                "4.9km",
                "5.0km",
                "5.0km",
                "5.1km",
                "5.1km",
                "5.2km",
                "5.2km",
                "5.3km",
                "5.4km",
                "5.4km",
                "5.5km",
                "5.5km",
                "5.6km",
                "5.6km",
                "5.7km",
                "5.8km",
                "5.8km",
                "5.9km",
                "5.9km",
                "6.0km",
                "6.0km",
                "6.1km",
                "6.1km",
                "6.2km",
                "6.2km",
                "6.3km",
                "6.4km",
                "6.4km",
                "6.5km",
                "6.5km",
                "6.6km",
                "6.6km",
                "6.7km",
                "6.7km",
                "6.8km",
                "6.9km",
                "6.9km",
                "7.0km",
                "7.0km",
                "7.1km",
                "7.1km",
                "7.2km",
                "7.2km",
                "7.3km",
                "7.4km",
                "7.4km",
                "7.5km",
                "7.5km",
                "7.6km",
                "7.6km",
                "7.7km",
                "7.7km",
                "7.8km",
                "7.8km",
                "7.9km",
                "7.9km",
                "8.0km"
            ],
            "data": [
                112.6,
                128.52631578947367,
                119.95,
                117.4,
                115.73684210526316,
                116.65,
                116.15,
                115.6842105263158,
                118.6,
                123.05,
                122.10526315789474,
                123.0,
                122.95,
                122.10526315789474,
                124.5,
                123.4,
                125.6842105263158,
                125.3,
                125.35,
                126.84210526315789,
                129.05,
                130.10526315789474,
                129.45,
                128.6,
                128.57894736842104,
                129.15,
                131.15,
                126.78947368421052,
                126.2,
                128.65,
                132.78947368421052,
                134.0,
                136.35,
                134.31578947368422,
                135.1,
                135.8,
                134.94736842105263,
                134.25,
                135.2,
                133.73684210526315,
                130.35,
                131.47368421052633,
                133.25,
                133.9,
                133.31578947368422,
                135.95,
                135.1,
                133.78947368421052,
                132.95,
                135.3,
                135.47368421052633,
                137.95,
                139.3,
                140.31578947368422,
                139.9,
                139.75,
                138.31578947368422,
                136.65,
                134.45,
                135.6315789473684,
                137.95,
                139.15,
                138.47368421052633,
                137.6,
                137.89473684210526,
                137.35,
                136.3,
                136.52631578947367,
                140.0,
                140.65,
                140.8421052631579,
                139.7,
                140.7,
                141.52631578947367,
                140.8,
                140.9,
                141.89473684210526,
                141.15,
                140.8,
                138.57894736842104,
                137.8,
                138.55,
                139.6315789473684,
                140.65,
                140.26315789473685,
                140.2,
                142.1,
                140.6315789473684,
                139.95,
                139.5,
                137.68421052631578,
                138.6,
                139.7,
                139.78947368421052,
                138.15,
                137.55,
                142.68421052631578,
                146.15,
                145.05,
                144.3684210526316,
                139.35,
                137.95,
                141.47368421052633,
                145.1,
                144.3,
                142.73684210526315,
                144.25,
                145.42105263157896,
                144.85,
                144.25,
                143.0,
                141.35,
                141.6,
                142.21052631578948,
                142.6,
                139.65,
                144.21052631578948,
                146.1,
                145.85,
                145.0,
                144.7,
                143.85,
                142.8421052631579,
                141.65,
                142.0,
                142.78947368421052,
                144.45,
                146.68421052631578,
                147.6,
                147.25,
                146.42105263157896,
                146.35,
                145.8,
                145.68421052631578,
                145.05,
                146.4,
                148.1578947368421,
                149.0,
                148.5,
                147.73684210526315,
                145.1,
                144.4,
                145.47368421052633,
                147.35,
                148.5,
                149.3684210526316,
                144.8,
                145.8421052631579
            ]
        }
    },
    "photos": [
        {
            "url": "https://picsum.photos/seed/1755813628000_a/600/400"
        },
        {
            "url": "https://picsum.photos/seed/1755813628000_b/600/400"
        }
    ]
}